tts/__init__.py
tts/gen_forward.py
tts/gen_tacotron.py
tts/main.py
tts/preprocess.py
tts/train_forward.py
tts/train_tacotron.py
tts/train_wavernn.py
tts/models/__init__.py
tts/models/common_layers.py
tts/models/deepmind_version.py
tts/models/fast_pitch.py
tts/models/fatchord_version.py
tts/models/forward_tacotron.py
tts/models/tacotron.py
tts/notebook_utils/__init__.py
tts/notebook_utils/synthesize.py
tts/tests/__init__.py
tts/tests/test_cleaner.py
tts/tests/test_collate_tts.py
tts/tests/test_dsp.py
tts/tests/test_forward_dataset.py
tts/tests/test_tokenizer.py
tts/trainer/__init__.py
tts/trainer/common.py
tts/trainer/forward_trainer.py
tts/trainer/taco_trainer.py
tts/trainer/voc_trainer.py
tts/utils/__init__.py
tts/utils/checkpoints.py
tts/utils/dataset.py
tts/utils/decorators.py
tts/utils/display.py
tts/utils/distribution.py
tts/utils/dsp.py
tts/utils/duration_extraction.py
tts/utils/files.py
tts/utils/metrics.py
tts/utils/paths.py
tts/utils/text/__init__.py
tts/utils/text/cleaners.py
tts/utils/text/numbers.py
tts/utils/text/recipes.py
tts/utils/text/symbols.py
tts/utils/text/tokenizer.py
CatalanTTSo-0.0.1.dist-info/METADATA
CatalanTTSo-0.0.1.dist-info/WHEEL
CatalanTTSo-0.0.1.dist-info/top_level.txt
CatalanTTSo-0.0.1.dist-info/RECORD
