Metadata-Version: 2.1
Name: CatalanTTSo
Version: 0.0.1
Summary: Catalan Text to Speech
Home-page: UNKNOWN
Author: Mehdi Hosseini Moghadam
Author-email: <m.h.moghadam1996@gmail.com>
License: UNKNOWN
Keywords: Catalan Text To Speech,Catalan TTS,Catalan,Catalan Speech,Catalan Speech Synthesis,Catalan Speech To Text,Catalan A.I.,Catalan Speech DataSet,Melgan,Catalan Speech Vocoder,Catalan Tacotron,Catalan FastSpeech,Catalan Speech To Text,Catalan ASR,Catalan Tacotron2
Platform: UNKNOWN
Classifier: Development Status :: 1 - Planning
Classifier: Intended Audience :: Developers
Classifier: Programming Language :: Python :: 3
Classifier: Operating System :: Unix
Classifier: Operating System :: MacOS :: MacOS X
Classifier: Operating System :: Microsoft :: Windows
Requires-Dist: numba (==0.49.1)
Requires-Dist: librosa (==0.7.2)
Requires-Dist: pyworld (>=0.2.10)
Requires-Dist: torch (>=1.2.0)
Requires-Dist: phonemizer (>=2.2)
Requires-Dist: webrtcvad (>=2.0.10)
Requires-Dist: PyYAML (>=5.1)
Requires-Dist: dataclasses
Requires-Dist: soundfile
Requires-Dist: scipy
Requires-Dist: tensorboard
Requires-Dist: matplotlib
Requires-Dist: unidecode
Requires-Dist: inflect
Requires-Dist: pydub
